<?xml version="1.0" encoding="utf-8" ?>
<channels>
  <!--通道1-->
  <channel>
    <no>1</no>
    <name>通道1</name>
    <!--通道虚拟IP，因为验证需要-->
    <channelvirtualip>172.21.4.100</channelvirtualip>
    <comserver>172.21.5.17</comserver>
    <pad>192.168.31.254</pad>
    <faceserver>172.21.5.190</faceserver>
    <camera>rtsp://172.21.5.1:8080/h264_ulaw.sdp</camera>
    <daycount>0</daycount>
  </channel>
  <channel>
    <no>2</no>
    <name>通道2</name>
    <!--通道虚拟IP，因为验证需要-->
    <channelvirtualip>172.21.4.100</channelvirtualip>
    <comserver></comserver>
    <pad></pad>
    <faceserver></faceserver>
    <camera></camera>
    <daycount>0</daycount>
  </channel>
  <channel>
    <no>3</no>
    <name>通道3</name>
    <!--通道虚拟IP，因为验证需要-->
    <channelvirtualip>172.21.4.100</channelvirtualip>
    <comserver></comserver>
    <pad></pad>
    <faceserver></faceserver>
    <camera></camera>
    <daycount>0</daycount>
  </channel>
  <channel>
    <no>4</no>
    <name>通道4</name>
    <!--通道虚拟IP，因为验证需要-->
    <channelvirtualip>172.21.4.100</channelvirtualip>
    <comserver></comserver>
    <pad></pad>
    <faceserver></faceserver>
    <camera></camera>
    <daycount>0</daycount>
  </channel>
  <channel>
    <no>5</no>
    <name>通道5</name>
    <!--通道虚拟IP，因为验证需要-->
    <channelvirtualip>172.21.4.100</channelvirtualip>
    <comserver></comserver>
    <pad></pad>
    <faceserver></faceserver>
    <camera></camera>
    <daycount>0</daycount>
  </channel>
  <channel>
    <no>6</no>
    <name>通道6</name>
    <!--通道虚拟IP，因为验证需要-->
    <channelvirtualip>172.21.4.100</channelvirtualip>
    <comserver></comserver>
    <pad></pad>
    <faceserver></faceserver>
    <camera></camera>
    <daycount>0</daycount>
  </channel>
  <channel>
    <no>7</no>
    <name>通道7</name>
    <!--通道虚拟IP，因为验证需要-->
    <channelvirtualip>172.21.4.100</channelvirtualip>
    <comserver></comserver>
    <pad></pad>
    <faceserver></faceserver>
    <camera></camera>
    <daycount>0</daycount>
  </channel>
  <channel>
    <no>8</no>
    <name>通道8</name>
    <!--通道虚拟IP，因为验证需要-->
    <channelvirtualip>172.21.4.100</channelvirtualip>
    <comserver></comserver>
    <pad></pad>
    <faceserver></faceserver>
    <camera></camera>
    <daycount>0</daycount>
  </channel>
  <channel>
    <no>9</no>
    <name>通道9</name>
    <!--通道虚拟IP，因为验证需要-->
    <channelvirtualip>172.21.4.100</channelvirtualip>
    <comserver></comserver>
    <pad></pad>
    <faceserver></faceserver>
    <camera></camera>
    <daycount>0</daycount>
  </channel>
  <channel>
    <no>10</no>
    <name>通道10</name>
    <!--通道虚拟IP，因为验证需要-->
    <channelvirtualip>172.21.4.100</channelvirtualip>
    <comserver></comserver>
    <pad></pad>
    <faceserver></faceserver>
    <camera></camera>
    <daycount>0</daycount>
  </channel>
  <channel>
    <no>11</no>
    <name>通道11</name>
    <!--通道虚拟IP，因为验证需要-->
    <channelvirtualip>172.21.4.100</channelvirtualip>
    <comserver></comserver>
    <pad></pad>
    <faceserver></faceserver>
    <camera></camera>
    <daycount>0</daycount>
  </channel>
  <channel>
    <no>12</no>
    <name>通道12</name>
    <!--通道虚拟IP，因为验证需要-->
    <channelvirtualip>172.21.4.100</channelvirtualip>
    <comserver></comserver>
    <pad></pad>
    <faceserver></faceserver>
    <camera></camera>
    <daycount>0</daycount>
  </channel>
</channels>
